codenode_python/__init__.py
codenode_python/class_definition.py
codenode_python/comment.py
codenode_python/conditional.py
codenode_python/docstring.py
codenode_python/for_loop.py
codenode_python/function_call.py
codenode_python/function_definition.py
codenode_python/match_statement.py
codenode_python/method.py
codenode_python/node.py
codenode_python/try_except.py
codenode_python/while_loop.py
codenode_python/with_block.py
codenode_python-1.0.dist-info/LICENSE
codenode_python-1.0.dist-info/METADATA
codenode_python-1.0.dist-info/WHEEL
codenode_python-1.0.dist-info/top_level.txt
codenode_python-1.0.dist-info/RECORD
