Metadata-Version: 2.1
Name: codenode-python
Version: 1.0
Summary: helpers for generating python using codenode
Home-page: https://github.com/0xf0f/codenode-python
Author: 0xf0f
Author-email: 0xf0f.dev@gmail.com
License: MIT
Classifier: Programming Language :: Python :: 3
Classifier: License :: OSI Approved :: MIT License
Classifier: Operating System :: OS Independent
Requires-Python: >=3.6
License-File: LICENSE
Requires-Dist: 0xf0f-codenode
